[
  {
    "sukuKata": "am.bah",
    "akarKata": null,
    "ejaan": "ambah",
    "baku": true,
    "alt": null,
    "makna": [
      {
        "tipe": "nomina",
        "tipeTeks": "kata benda",
        "definisi": "pertukangan",
        "contoh": null,
        "info": [
          {
            "sumber": "arkais",
            "sumberTeks": "menandai kata yang tidak lazim"
          }
        ]
      }
    ]
  },
  {
    "sukuKata": "am.bah",
    "akarKata": null,
    "ejaan": "ambah",
    "baku": true,
    "alt": null,
    "makna": [
      {
        "tipe": "nomina",
        "tipeTeks": "kata benda",
        "definisi": "gerak-gerik yang  tidak menyenangkan sebagai ungkapan rasa marah",
        "contoh": "ke manakah -- ini akan kulepaskan",
        "info": [
          {
            "sumber": "melayu riau",
            "sumberTeks": null
          }
        ]
      }
    ]
  },
  {
    "sukuKata": "am.bah",
    "akarKata": null,
    "ejaan": "ambah",
    "baku": true,
    "alt": null,
    "makna": [
      {
        "tipe": "adjektiva",
        "tipeTeks": "kata yang menjelaskan nomina atau pronomina",
        "definisi": "tidak banyak pantang",
        "contoh": null,
        "info": [
          {
            "sumber": "minangkabau",
            "sumberTeks": null
          }
        ]
      }
    ]
  }
]