[
  {
    "sukuKata": "awang",
    "akarKata": null,
    "ejaan": "awang",
    "baku": true,
    "alt": null,
    "makna": [
      {
        "tipe": "nomina",
        "tipeTeks": "kata benda",
        "definisi": "kata sapaan kepada anak muda (terutama anak sulung)",
        "contoh": null,
        "info": []
      },
      {
        "tipe": "nomina",
        "tipeTeks": "kata benda",
        "definisi": "kata sapaan kepada orang laki-laki",
        "contoh": "-- dan dayang",
        "info": []
      }
    ]
  },
  {
    "sukuKata": "awang",
    "akarKata": null,
    "ejaan": "awang",
    "baku": true,
    "alt": null,
    "makna": [
      {
        "definisi": "kata sapaan kepada anak muda (terutama anak sulung)",
        "contoh": null,
        "info": []
      },
      {
        "definisi": "kata sapaan kepada orang laki-laki",
        "contoh": null,
        "info": []
      }
    ]
  },
  {
    "sukuKata": "awang",
    "akarKata": null,
    "ejaan": "awang",
    "baku": true,
    "alt": null,
    "makna": [
      {
        "tipe": "prakategorial",
        "tipeTeks": "kata tidak dipakai dalam bentuk dasarnya",
        "referensi": [
          "berawang"
        ]
      }
    ]
  }
]