[
  {
    "sukuKata": "ba.ger",
    "akarKata": null,
    "ejaan": "bagêr",
    "baku": true,
    "alt": null,
    "makna": [
      {
        "tipe": "adjektiva",
        "tipeTeks": "kata yang menjelaskan nomina atau pronomina",
        "definisi": "baik",
        "contoh": "saat pertama kali menginjakkan kaki di Arab Saudi, dia berharap mendapatkan majikan yang --",
        "info": [
          {
            "sumber": "sunda",
            "sumberTeks": null
          }
        ]
      }
    ]
  }
]