[
  {
    "sukuKata": "bu.ras",
    "akarKata": null,
    "ejaan": "buras",
    "baku": true,
    "alt": null,
    "makna": [
      {
        "tipe": "nomina",
        "tipeTeks": "kata benda",
        "definisi": "omongan; cakap; obrolan",
        "contoh": null,
        "info": []
      }
    ]
  },
  {
    "sukuKata": "bu.ras",
    "akarKata": null,
    "ejaan": "buras",
    "baku": true,
    "alt": null,
    "makna": [
      {
        "tipe": "nomina",
        "tipeTeks": "kata benda",
        "definisi": "penganan, dibuat dari beras dan santan, dibungkus dengan daun pisang, dan dikukus; lontong bersantan",
        "contoh": null,
        "info": []
      }
    ]
  },
  {
    "sukuKata": "bu.ras",
    "akarKata": null,
    "ejaan": "buras",
    "baku": true,
    "alt": null,
    "makna": [
      {
        "tipe": "nomina",
        "tipeTeks": "kata benda",
        "definisi": "persengketaan atau perselisihan yang tidak dapat diselesaikan; proses peradilan yang tidak memenangkan salah satu pihak yang berperkara",
        "contoh": null,
        "info": []
      }
    ]
  },
  {
    "sukuKata": "bu.ras",
    "akarKata": null,
    "ejaan": "buras",
    "baku": true,
    "alt": null,
    "makna": [
      {
        "definisi": "persengketaan atau perselisihan yang tidak dapat diselesaikan; proses peradilan yang tidak memenangkan salah satu pihak yang berperkara",
        "contoh": null,
        "info": []
      }
    ]
  },
  {
    "sukuKata": "bu.ras",
    "akarKata": null,
    "ejaan": "buras",
    "baku": true,
    "alt": null,
    "makna": [
      {
        "tipe": "nomina",
        "tipeTeks": "kata benda",
        "definisi": "penyakit kulit yang berupa bercak-bercak putih",
        "contoh": null,
        "info": []
      }
    ]
  },
  {
    "sukuKata": "bu.ras",
    "akarKata": null,
    "ejaan": "buras",
    "baku": true,
    "alt": null,
    "makna": [
      {
        "tipe": "nomina",
        "tipeTeks": "kata benda",
        "definisi": "bukan ras (tentang ayam)",
        "contoh": null,
        "info": [
          {
            "sumber": "akronim"
          }
        ]
      }
    ]
  }
]