[
  {
    "sukuKata": "DPO",
    "akarKata": null,
    "ejaan": "DPO",
    "baku": true,
    "alt": null,
    "makna": [
      {
        "tipe": "nomina",
        "tipeTeks": "kata benda",
        "definisi": "daftar pencarian orang (daftar orang-orang yang dicari atau menjadi target pihak aparat kepolisian, secara umum merujuk kepada orang hilang dan pelaku kriminal)",
        "contoh": null,
        "info": [
          {
            "sumber": "singkatan"
          }
        ]
      }
    ]
  }
]