[
  {
    "sukuKata": "je.rok",
    "akarKata": null,
    "ejaan": "jérok",
    "baku": true,
    "alt": null,
    "makna": [
      {
        "tipe": "nomina",
        "tipeTeks": "kata benda",
        "definisi": "masakan khas Bugis, dibuat dari parutan pepaya muda dicampur taoge yang sudah dikukus, bumbu dapur, kelapa goreng, dan telur udang, biasanya disantap pada acara-acara setengah resmi atau sebelum hari pelaksanaan pesta perkawinan",
        "contoh": null,
        "info": [
          {
            "sumber": "bugis",
            "sumberTeks": null
          }
        ]
      }
    ]
  }
]