[
  {
    "sukuKata": "jo.get",
    "akarKata": null,
    "ejaan": "jogèt",
    "baku": true,
    "alt": "joged",
    "makna": [
      {
        "tipe": "nomina",
        "tipeTeks": "kata benda",
        "definisi": "tari (sebarang tarian)",
        "contoh": null,
        "info": [
          {
            "sumber": "kesenian",
            "sumberTeks": null
          }
        ]
      },
      {
        "tipe": "nomina",
        "tipeTeks": "kata benda",
        "definisi": "tarian dan lagu Melayu yang agak rancak iramanya",
        "contoh": null,
        "info": [
          {
            "sumber": "kesenian",
            "sumberTeks": null
          }
        ]
      },
      {
        "tipe": "nomina",
        "tipeTeks": "kata benda",
        "definisi": "andak; ronggeng",
        "contoh": null,
        "info": [
          {
            "sumber": "kesenian",
            "sumberTeks": null
          }
        ]
      }
    ]
  }
]