[
  {
    "sukuKata": "ke.ren",
    "akarKata": null,
    "ejaan": "kêrèn",
    "baku": true,
    "alt": null,
    "makna": [
      {
        "tipe": "adjektiva",
        "tipeTeks": "kata yang menjelaskan nomina atau pronomina",
        "definisi": "tampak gagah dan tangkas",
        "contoh": null,
        "info": []
      },
      {
        "tipe": "adjektiva",
        "tipeTeks": "kata yang menjelaskan nomina atau pronomina",
        "definisi": "galak; garang; lekas marah",
        "contoh": null,
        "info": []
      },
      {
        "tipe": "adjektiva",
        "tipeTeks": "kata yang menjelaskan nomina atau pronomina",
        "definisi": "lekas berlari cepat (tentang kuda)",
        "contoh": null,
        "info": []
      },
      {
        "tipe": "adjektiva",
        "tipeTeks": "kata yang menjelaskan nomina atau pronomina",
        "definisi": "perlente (berpakaian bagus, berdandan rapi, dan sebagainya)",
        "contoh": null,
        "info": []
      }
    ]
  }
]