[
  {
    "sukuKata": "ki.sik",
    "akarKata": null,
    "ejaan": "kisik",
    "baku": true,
    "alt": null,
    "makna": [
      {
        "tipe": "nomina",
        "tipeTeks": "kata benda",
        "definisi": "bisik",
        "contoh": null,
        "info": [
          {
            "sumber": "melayu jakarta",
            "sumberTeks": null
          }
        ]
      }
    ]
  },
  {
    "sukuKata": "ki.sik",
    "akarKata": null,
    "ejaan": "kisik",
    "baku": true,
    "alt": null,
    "makna": [
      {
        "tipe": "verba",
        "tipeTeks": "kata kerja",
        "definisi": "tumbuk pelan-pelan",
        "contoh": null,
        "info": [
          {
            "sumber": "minangkabau",
            "sumberTeks": null
          }
        ]
      }
    ]
  }
]