[
  {
    "sukuKata": "om.pok",
    "akarKata": null,
    "ejaan": "ompok",
    "baku": true,
    "alt": null,
    "makna": [
      {
        "tipe": "nomina",
        "tipeTeks": "kata benda",
        "definisi": "ikan air tawar yang ukurannya dapat mencapai 45 cm, tubuhnya pipih memanjang dengan sirip punggung pendek, matanya terletak di belakang sudut mulut, warnanya kecokelatan dengan bercak kehitaman di atas pangkal sirip dada, tersebar di perairan Indocina, India, dan Indonesia (Sumatra, Jawa, dan Kalimantan)",
        "contoh": null,
        "info": []
      }
    ]
  }
]