[
  {
    "sukuKata": "pa.reo",
    "akarKata": null,
    "ejaan": "paréo",
    "baku": true,
    "alt": null,
    "makna": [
      {
        "tipe": "nomina",
        "tipeTeks": "kata benda",
        "definisi": "sarung atau secarik kain bercorak bunga-bungaan dengan warna-warni mencolok, dililitkan di tubuh bagian bawah, berasal dari kepulauan Polinesia, sangat populer sebagai busana pantai",
        "contoh": null,
        "info": [
          {
            "sumber": "tata busana",
            "sumberTeks": null
          }
        ]
      }
    ]
  }
]