[
  {
    "sukuKata": "Pel.ni",
    "akarKata": null,
    "ejaan": "pêlni",
    "baku": true,
    "alt": null,
    "makna": [
      {
        "tipe": "nomina",
        "tipeTeks": "kata benda",
        "definisi": "Pelayaran Nasional Indonesia (perusahaan pelayaran nasional yang menyediakan jasa transportasi laut, meliputi jasa angkutan penumpang, dan muatan barang antarpulau)",
        "contoh": null,
        "info": [
          {
            "sumber": "akronim"
          }
        ]
      }
    ]
  }
]