[
  {
    "sukuKata": "pen.si",
    "akarKata": null,
    "ejaan": "pènsi",
    "baku": true,
    "alt": null,
    "makna": [
      {
        "tipe": "nomina",
        "tipeTeks": "kata benda",
        "definisi": "lokan kecil yang hidup di danau-danau dan dagingnya dapat dimakan",
        "contoh": null,
        "info": [
          {
            "sumber": "minangkabau",
            "sumberTeks": null
          }
        ]
      }
    ]
  },
  {
    "sukuKata": "pen.si",
    "akarKata": null,
    "ejaan": "pênsi",
    "baku": true,
    "alt": null,
    "makna": [
      {
        "tipe": "nomina",
        "tipeTeks": "kata benda",
        "definisi": "pentas seni",
        "contoh": null,
        "info": [
          {
            "sumber": "akronim"
          }
        ]
      }
    ]
  }
]