[
  {
    "sukuKata": "su.lut",
    "akarKata": null,
    "ejaan": "sulut",
    "baku": true,
    "alt": null,
    "makna": [
      {
        "tipe": "verba",
        "tipeTeks": "kata kerja",
        "definisi": "sundut",
        "contoh": null,
        "info": []
      }
    ]
  },
  {
    "sukuKata": "Su.lut",
    "akarKata": null,
    "ejaan": "Sulut",
    "baku": true,
    "alt": null,
    "makna": [
      {
        "tipe": "nomina",
        "tipeTeks": "kata benda",
        "definisi": "Sulawesi Utara",
        "contoh": null,
        "info": [
          {
            "sumber": "akronim"
          }
        ]
      }
    ]
  }
]