[
  {
    "sukuKata": "ta.nin",
    "akarKata": null,
    "ejaan": "tanin",
    "baku": true,
    "alt": null,
    "makna": [
      {
        "tipe": "nomina",
        "tipeTeks": "kata benda",
        "definisi": "kumpulan senyawa organik amorf yang bersifat asam dengan rasa sepat, ditemukan dalam banyak tumbuhan, digunakan sebagai bahan penyamak, bahan pembuat tinta, dan bahan pewarna",
        "contoh": null,
        "info": [
          {
            "sumber": "kimia",
            "sumberTeks": null
          }
        ]
      }
    ]
  }
]